{
  "annotations": {
    "list": [
      {
        "builtIn": 1,
        "datasource": "-- Grafana --",
        "enable": true,
        "hide": true,
        "iconColor": "rgba(0, 211, 255, 1)",
        "name": "Annotations & Alerts",
        "target": {
          "limit": 100,
          "matchAny": false,
          "tags": [],
          "type": "dashboard"
        },
        "type": "dashboard"
      }
    ]
  },
  "description": "Visualize AWS S3 metrics",
  "editable": true,
  "gnetId": 575,
  "graphTooltip": 0,
  "id": 28,
  "iteration": 1632766728960,
  "links": [],
  "panels": [
    {
      "aliasColors": {},
      "bars": false,
      "dashLength": 10,
      "dashes": false,
      "datasource": "$datasource",
      "editable": true,
      "error": false,
      "fieldConfig": {
        "defaults": {
          "links": []
        },
        "overrides": []
      },
      "fill": 1,
      "fillGradient": 0,
      "grid": {},
      "gridPos": {
        "h": 7,
        "w": 24,
        "x": 0,
        "y": 0
      },
      "hiddenSeries": false,
      "id": 1,
      "isNew": true,
      "legend": {
        "alignAsTable": true,
        "avg": true,
        "current": true,
        "max": true,
        "min": true,
        "show": true,
        "sort": "current",
        "sortDesc": true,
        "total": false,
        "values": true
      },
      "lines": true,
      "linewidth": 2,
      "links": [],
      "nullPointMode": "connected",
      "options": {
        "alertThreshold": true
      },
      "percentage": false,
      "pluginVersion": "8.1.5",
      "pointradius": 5,
      "points": false,
      "renderer": "flot",
      "seriesOverrides": [],
      "spaceLength": 10,
      "stack": false,
      "steppedLine": false,
      "targets": [
        {
          "alias": "{{BucketName}}",
          "application": {
            "filter": ""
          },
          "dimensions": {
            "BucketName": "$bucket",
            "StorageType": "StandardStorage"
          },
          "expression": "",
          "functions": [],
          "group": {
            "filter": ""
          },
          "highResolution": false,
          "host": {
            "filter": ""
          },
          "id": "",
          "item": {
            "filter": ""
          },
          "matchExact": true,
          "metricName": "BucketSizeBytes",
          "mode": 0,
          "namespace": "AWS/S3",
          "options": {
            "showDisabledItems": false
          },
          "period": "",
          "refId": "A",
          "region": "$region",
          "returnData": false,
          "statistics": [
            "Average"
          ]
        }
      ],
      "thresholds": [],
      "timeFrom": null,
      "timeRegions": [],
      "timeShift": null,
      "title": "BucketSizeBytes",
      "tooltip": {
        "msResolution": false,
        "shared": true,
        "sort": 0,
        "value_type": "cumulative"
      },
      "type": "graph",
      "xaxis": {
        "buckets": null,
        "mode": "time",
        "name": null,
        "show": true,
        "values": []
      },
      "yaxes": [
        {
          "format": "bytes",
          "label": null,
          "logBase": 1,
          "max": null,
          "min": 0,
          "show": true
        },
        {
          "format": "short",
          "label": null,
          "logBase": 1,
          "max": null,
          "min": null,
          "show": false
        }
      ],
      "yaxis": {
        "align": false,
        "alignLevel": null
      }
    },
    {
      "aliasColors": {},
      "bars": false,
      "dashLength": 10,
      "dashes": false,
      "datasource": "$datasource",
      "editable": true,
      "error": false,
      "fieldConfig": {
        "defaults": {
          "links": []
        },
        "overrides": []
      },
      "fill": 1,
      "fillGradient": 0,
      "grid": {},
      "gridPos": {
        "h": 7,
        "w": 24,
        "x": 0,
        "y": 7
      },
      "hiddenSeries": false,
      "id": 3,
      "isNew": true,
      "legend": {
        "alignAsTable": true,
        "avg": true,
        "current": true,
        "max": true,
        "min": true,
        "show": true,
        "sort": "current",
        "sortDesc": true,
        "total": false,
        "values": true
      },
      "lines": true,
      "linewidth": 2,
      "links": [],
      "nullPointMode": "connected",
      "options": {
        "alertThreshold": true
      },
      "percentage": false,
      "pluginVersion": "8.1.5",
      "pointradius": 5,
      "points": false,
      "renderer": "flot",
      "seriesOverrides": [],
      "spaceLength": 10,
      "stack": false,
      "steppedLine": false,
      "targets": [
        {
          "alias": "{{BucketName}}",
          "application": {
            "filter": ""
          },
          "dimensions": {
            "BucketName": "$bucket",
            "StorageType": "AllStorageTypes"
          },
          "expression": "",
          "functions": [],
          "group": {
            "filter": ""
          },
          "highResolution": false,
          "host": {
            "filter": ""
          },
          "id": "",
          "item": {
            "filter": ""
          },
          "matchExact": true,
          "metricName": "NumberOfObjects",
          "mode": 0,
          "namespace": "AWS/S3",
          "options": {
            "showDisabledItems": false
          },
          "period": "",
          "refId": "A",
          "region": "$region",
          "returnData": false,
          "statistics": [
            "Average"
          ]
        }
      ],
      "thresholds": [],
      "timeFrom": null,
      "timeRegions": [],
      "timeShift": null,
      "title": "NumberOfObjects",
      "tooltip": {
        "msResolution": false,
        "shared": true,
        "sort": 0,
        "value_type": "cumulative"
      },
      "type": "graph",
      "xaxis": {
        "buckets": null,
        "mode": "time",
        "name": null,
        "show": true,
        "values": []
      },
      "yaxes": [
        {
          "format": "none",
          "label": null,
          "logBase": 1,
          "max": null,
          "min": 0,
          "show": true
        },
        {
          "format": "short",
          "label": null,
          "logBase": 1,
          "max": null,
          "min": null,
          "show": false
        }
      ],
      "yaxis": {
        "align": false,
        "alignLevel": null
      }
    }
  ],
  "refresh": false,
  "schemaVersion": 30,
  "style": "dark",
  "tags": [],
  "templating": {
    "list": [
      {
        "current": {
          "selected": true,
          "text": "AWS - simplilearn2",
          "value": "AWS - simplilearn2"
        },
        "description": null,
        "error": null,
        "hide": 0,
        "includeAll": false,
        "label": "Datasource",
        "multi": false,
        "name": "datasource",
        "options": [],
        "query": "cloudwatch",
        "queryValue": "",
        "refresh": 1,
        "regex": "",
        "skipUrlSync": false,
        "type": "datasource"
      },
      {
        "allValue": null,
        "current": {
          "selected": false,
          "text": "us-east-1",
          "value": "us-east-1"
        },
        "datasource": "$datasource",
        "definition": "regions()",
        "description": null,
        "error": null,
        "hide": 0,
        "includeAll": false,
        "label": "Region",
        "multi": false,
        "name": "region",
        "options": [],
        "query": "regions()",
        "refresh": 1,
        "regex": "",
        "skipUrlSync": false,
        "sort": 0,
        "tagValuesQuery": "",
        "tagsQuery": "",
        "type": "query",
        "useTags": false
      },
      {
        "allValue": "",
        "current": {
          "selected": false,
          "text": "amplify-graphqlapp-dev-102914-deployment",
          "value": "amplify-graphqlapp-dev-102914-deployment"
        },
        "datasource": "$datasource",
        "definition": "dimension_values($region,AWS/S3,NumberOfObjects,BucketName)",
        "description": null,
        "error": null,
        "hide": 0,
        "includeAll": false,
        "label": "Bucket",
        "multi": true,
        "name": "bucket",
        "options": [],
        "query": "dimension_values($region,AWS/S3,NumberOfObjects,BucketName)",
        "refresh": 1,
        "regex": "",
        "skipUrlSync": false,
        "sort": 1,
        "tagValuesQuery": "",
        "tagsQuery": "",
        "type": "query",
        "useTags": false
      },
      {
        "allValue": null,
        "current": {
          "isNone": true,
          "selected": false,
          "text": "None",
          "value": ""
        },
        "datasource": "$datasource",
        "definition": "dimension_values($region,AWS/S3,AllRequests,FilterId)",
        "description": null,
        "error": null,
        "hide": 0,
        "includeAll": false,
        "label": "FilterId",
        "multi": false,
        "name": "filterid",
        "options": [],
        "query": "dimension_values($region,AWS/S3,AllRequests,FilterId)",
        "refresh": 1,
        "regex": "",
        "skipUrlSync": false,
        "sort": 1,
        "tagValuesQuery": "",
        "tagsQuery": "",
        "type": "query",
        "useTags": false
      }
    ]
  },
  "time": {
    "from": "now-30d",
    "to": "now"
  },
  "timepicker": {
    "refresh_intervals": [
      "5s",
      "10s",
      "30s",
      "1m",
      "5m",
      "15m",
      "30m",
      "1h",
      "2h",
      "1d"
    ],
    "time_options": [
      "5m",
      "15m",
      "1h",
      "6h",
      "12h",
      "24h",
      "2d",
      "7d",
      "30d"
    ]
  },
  "timezone": "browser",
  "title": "AWS S3",
  "uid": "yyJEceV7k",
  "version": 1
}